[
  {
    "name": "global",
    "display": "グローバル",
    "items": [
      {
        "key": "season_start",
        "display": "最初の季節",
        "index": 0,
        "options": ["default", "winter", "spring", "summer", "autumn|spring", "winter|summer", "autumn|winter|spring|summer"],
        "opts-display": ["秋", "冬", "春", "夏", "秋か春", "冬または夏", "ランダム"]
      }
    ]
  },
  {
    "name": "misc",
    "display": "世界",
    "items": [
      {
        "key": "boons",
        "display": "倒れた冒険者",
        "index": 3,
        "options": ["never", "rare", "uncommon", "default", "often", "mostly", "always", "insane"],
        "opts-display": ["なし", "ちっこい", "少ない", "デフォルト", "もっと", "いっぱい", "いっぱい", "インセイン"]
      },
      {
        "key": "branching",
        "display": "枝",
        "index": 2,
        "options": ["never", "least", "default", "most", "random"],
        "opts-display": ["ありえない", "一番少ない", "デフォルト", "一番", "ランダム"]
      },
      {
        "key": "loop",
        "display": "ループ",
        "index": 1,
        "options": ["never", "default", "always"],
        "opts-display": ["ありえない", "デフォルト", "いつも"]
      },
      {
        "key": "moon_fissure",
        "display": "天体の亀裂",
        "index": 3,
        "options": ["never", "rare", "uncommon", "default", "often", "mostly", "always", "insane"],
        "opts-display": ["なし", "ちっこい", "少ない", "デフォルト", "もっと", "いっぱい", "いっぱい", "インセイン"]
      },
      {
        "key": "prefabswaps_start",
        "display": "スタート時の素材の種類",
        "index": 1,
        "options": ["classic", "default", "highly random"],
        "opts-display": ["クラシック", "デフォルト", "かなりランダム"]
      },
      {
        "key": "roads",
        "display": "道",
        "index": 1,
        "options": ["never", "default"],
        "opts-display": ["なし", "デフォルト"]
      },
      {
        "key": "stageplays",
        "display": "舞台劇",
        "index": 1,
        "options": ["never", "default"],
        "opts-display": ["なし", "デフォルト"]
      },
      {
        "key": "start_location",
        "display": "産卵領域",
        "index": 0,
        "options": ["default", "plus", "darkness"],
        "opts-display": ["デフォルト", "準備万端", "暗い"]
      },
      {
        "key": "task_set",
        "display": "生物",
        "index": 0,
        "options": ["default", "classic"],
        "opts-display": ["Together", "クラシック"]
      },
      {
        "key": "terrariumchest",
        "display": "テラリウム",
        "index": 1,
        "options": ["never", "default"],
        "opts-display": ["なし", "デフォルト"]
      },
      {
        "key": "touchstone",
        "display": "死に戻りの標",
        "index": 3,
        "options": ["never", "rare", "uncommon", "default", "often", "mostly", "always", "insane"],
        "opts-display": ["なし", "ちっこい", "少ない", "デフォルト", "もっと", "いっぱい", "いっぱい", "インセイン"]
      },
      {
        "key": "world_size",
        "display": "ワールドのサイズ",
        "index": 2,
        "options": ["small", "medium", "default", "huge"],
        "opts-display": ["ちっぽけな", "ミディアム", "大きい", "巨大"]
      }
    ]
  },
  {
    "name": "resources",
    "display": "資源",
    "items": [
      {
        "key": "berrybush",
        "display": "木イチゴの低木",
        "index": 3,
        "options": ["never", "rare", "uncommon", "default", "often", "mostly", "always", "insane"],
        "opts-display": ["なし", "ちっこい", "少ない", "デフォルト", "もっと", "いっぱい", "いっぱい", "インセイン"]
      },
      {
        "key": "cactus",
        "display": "サボテン",
        "index": 3,
        "options": ["never", "rare", "uncommon", "default", "often", "mostly", "always", "insane"],
        "opts-display": ["なし", "ちっこい", "少ない", "デフォルト", "もっと", "いっぱい", "いっぱい", "インセイン"]
      },
      {
        "key": "carrot",
        "display": "ニンジン",
        "index": 3,
        "options": ["never", "rare", "uncommon", "default", "often", "mostly", "always", "insane"],
        "opts-display": ["なし", "ちっこい", "少ない", "デフォルト", "もっと", "いっぱい", "いっぱい", "インセイン"]
      },
      {
        "key": "flint",
        "display": "フリント",
        "index": 3,
        "options": ["never", "rare", "uncommon", "default", "often", "mostly", "always", "insane"],
        "opts-display": ["なし", "ちっこい", "少ない", "デフォルト", "もっと", "いっぱい", "いっぱい", "インセイン"]
      },
      {
        "key": "flowers",
        "display": "花/イーブルフラワー",
        "index": 3,
        "options": ["never", "rare", "uncommon", "default", "often", "mostly", "always", "insane"],
        "opts-display": ["なし", "ちっこい", "少ない", "デフォルト", "もっと", "いっぱい", "いっぱい", "インセイン"]
      },
      {
        "key": "grass",
        "display": "草",
        "index": 3,
        "options": ["never", "rare", "uncommon", "default", "often", "mostly", "always", "insane"],
        "opts-display": ["なし", "ちっこい", "少ない", "デフォルト", "もっと", "いっぱい", "いっぱい", "インセイン"]
      },
      {
        "key": "marshbush",
        "display": "トゲトゲの茂み",
        "index": 3,
        "options": ["never", "rare", "uncommon", "default", "often", "mostly", "always", "insane"],
        "opts-display": ["なし", "ちっこい", "少ない", "デフォルト", "もっと", "いっぱい", "いっぱい", "インセイン"]
      },
      {
        "key": "meteorspawner",
        "display": "いん石墜落跡",
        "index": 3,
        "options": ["never", "rare", "uncommon", "default", "often", "mostly", "always", "insane"],
        "opts-display": ["なし", "ちっこい", "少ない", "デフォルト", "もっと", "いっぱい", "いっぱい", "インセイン"]
      },
      {
        "key": "moon_berrybush",
        "display": "石フルーツの茂み",
        "index": 3,
        "options": ["never", "rare", "uncommon", "default", "often", "mostly", "always", "insane"],
        "opts-display": ["なし", "ちっこい", "少ない", "デフォルト", "もっと", "いっぱい", "いっぱい", "インセイン"]
      },
      {
        "key": "moon_bullkelp",
        "display": "ブル昆布の漂着",
        "index": 3,
        "options": ["never", "rare", "uncommon", "default", "often", "mostly", "always", "insane"],
        "opts-display": ["なし", "ちっこい", "少ない", "デフォルト", "もっと", "いっぱい", "いっぱい", "インセイン"]
      },
      {
        "key": "moon_hotspring",
        "display": "温泉",
        "index": 3,
        "options": ["never", "rare", "uncommon", "default", "often", "mostly", "always", "insane"],
        "opts-display": ["なし", "ちっこい", "少ない", "デフォルト", "もっと", "いっぱい", "いっぱい", "インセイン"]
      },
      {
        "key": "moon_rock",
        "display": "月の岩",
        "index": 3,
        "options": ["never", "rare", "uncommon", "default", "often", "mostly", "always", "insane"],
        "opts-display": ["なし", "ちっこい", "少ない", "デフォルト", "もっと", "いっぱい", "いっぱい", "インセイン"]
      },
      {
        "key": "moon_sapling",
        "display": "月の胞子",
        "index": 3,
        "options": ["never", "rare", "uncommon", "default", "often", "mostly", "always", "insane"],
        "opts-display": ["なし", "ちっこい", "少ない", "デフォルト", "もっと", "いっぱい", "いっぱい", "インセイン"]
      },
      {
        "key": "moon_starfish",
        "display": "アネネミー",
        "index": 3,
        "options": ["never", "rare", "uncommon", "default", "often", "mostly", "always", "insane"],
        "opts-display": ["なし", "ちっこい", "少ない", "デフォルト", "もっと", "いっぱい", "いっぱい", "インセイン"]
      },
      {
        "key": "moon_tree",
        "display": "三日月の木",
        "index": 3,
        "options": ["never", "rare", "uncommon", "default", "often", "mostly", "always", "insane"],
        "opts-display": ["なし", "ちっこい", "少ない", "デフォルト", "もっと", "いっぱい", "いっぱい", "インセイン"]
      },
      {
        "key": "mushroom",
        "display": "キノコ",
        "index": 3,
        "options": ["never", "rare", "uncommon", "default", "often", "mostly", "always", "insane"],
        "opts-display": ["なし", "ちっこい", "少ない", "デフォルト", "もっと", "いっぱい", "いっぱい", "インセイン"]
      },
      {
        "key": "ocean_bullkelp",
        "display": "ブル昆布",
        "index": 3,
        "options": ["never", "rare", "uncommon", "default", "often", "mostly", "always", "insane"],
        "opts-display": ["なし", "ちっこい", "少ない", "デフォルト", "もっと", "いっぱい", "いっぱい", "インセイン"]
      },
      {
        "key": "ocean_seastack",
        "display": "海食柱",
        "index": 3,
        "options": ["ocean_never", "ocean_rare", "ocean_uncommon", "ocean_default", "ocean_often", "ocean_mostly", "ocean_always", "ocean_insane"],
        "opts-display": ["なし", "ちっこい", "少ない", "デフォルト", "もっと", "いっぱい", "いっぱい", "インセイン"]
      },
      {
        "key": "palmconetree",
        "display": "パルムコーンの木",
        "index": 3,
        "options": ["never", "rare", "uncommon", "default", "often", "mostly", "always", "insane"],
        "opts-display": ["なし", "ちっこい", "少ない", "デフォルト", "もっと", "いっぱい", "いっぱい", "インセイン"]
      },
      {
        "key": "ponds",
        "display": "池",
        "index": 3,
        "options": ["never", "rare", "uncommon", "default", "often", "mostly", "always", "insane"],
        "opts-display": ["なし", "ちっこい", "少ない", "デフォルト", "もっと", "いっぱい", "いっぱい", "インセイン"]
      },
      {
        "key": "reeds",
        "display": "アシ",
        "index": 3,
        "options": ["never", "rare", "uncommon", "default", "often", "mostly", "always", "insane"],
        "opts-display": ["なし", "ちっこい", "少ない", "デフォルト", "もっと", "いっぱい", "いっぱい", "インセイン"]
      },
      {
        "key": "rock",
        "display": "岩",
        "index": 3,
        "options": ["never", "rare", "uncommon", "default", "often", "mostly", "always", "insane"],
        "opts-display": ["なし", "ちっこい", "少ない", "デフォルト", "もっと", "いっぱい", "いっぱい", "インセイン"]
      },
      {
        "key": "rock_ice",
        "display": "氷河片",
        "index": 3,
        "options": ["never", "rare", "uncommon", "default", "often", "mostly", "always", "insane"],
        "opts-display": ["なし", "ちっこい", "少ない", "デフォルト", "もっと", "いっぱい", "いっぱい", "インセイン"]
      },
      {
        "key": "sapling",
        "display": "苗木",
        "index": 3,
        "options": ["never", "rare", "uncommon", "default", "often", "mostly", "always", "insane"],
        "opts-display": ["なし", "ちっこい", "少ない", "デフォルト", "もっと", "いっぱい", "いっぱい", "インセイン"]
      },
      {
        "key": "trees",
        "display": "木(全種類)",
        "index": 3,
        "options": ["never", "rare", "uncommon", "default", "often", "mostly", "always", "insane"],
        "opts-display": ["なし", "ちっこい", "少ない", "デフォルト", "もっと", "いっぱい", "いっぱい", "インセイン"]
      },
      {
        "key": "tumbleweed",
        "display": "回転草",
        "index": 3,
        "options": ["never", "rare", "uncommon", "default", "often", "mostly", "always", "insane"],
        "opts-display": ["なし", "ちっこい", "少ない", "デフォルト", "もっと", "いっぱい", "いっぱい", "インセイン"]
      }
    ]
  },
  {
    "name": "animals",
    "display": "生物とスポナー",
    "items": [
      {
        "key": "beefalo",
        "display": "ビーファロー",
        "index": 3,
        "options": ["never", "rare", "uncommon", "default", "often", "mostly", "always", "insane"],
        "opts-display": ["なし", "ちっこい", "少ない", "デフォルト", "もっと", "いっぱい", "いっぱい", "インセイン"]
      },
      {
        "key": "bees",
        "display": "蜂の巣",
        "index": 3,
        "options": ["never", "rare", "uncommon", "default", "often", "mostly", "always", "insane"],
        "opts-display": ["なし", "ちっこい", "少ない", "デフォルト", "もっと", "いっぱい", "いっぱい", "インセイン"]
      },
      {
        "key": "buzzard",
        "display": "ハゲタカ",
        "index": 3,
        "options": ["never", "rare", "uncommon", "default", "often", "mostly", "always", "insane"],
        "opts-display": ["なし", "ちっこい", "少ない", "デフォルト", "もっと", "いっぱい", "いっぱい", "インセイン"]
      },
      {
        "key": "catcoon",
        "display": "空洞の切り株",
        "index": 3,
        "options": ["never", "rare", "uncommon", "default", "often", "mostly", "always", "insane"],
        "opts-display": ["なし", "ちっこい", "少ない", "デフォルト", "もっと", "いっぱい", "いっぱい", "インセイン"]
      },
      {
        "key": "lightninggoat",
        "display": "サンダーゴート",
        "index": 3,
        "options": ["never", "rare", "uncommon", "default", "often", "mostly", "always", "insane"],
        "opts-display": ["なし", "ちっこい", "少ない", "デフォルト", "もっと", "いっぱい", "いっぱい", "インセイン"]
      },
      {
        "key": "moles",
        "display": "モグラの巣穴",
        "index": 3,
        "options": ["never", "rare", "uncommon", "default", "often", "mostly", "always", "insane"],
        "opts-display": ["なし", "ちっこい", "少ない", "デフォルト", "もっと", "いっぱい", "いっぱい", "インセイン"]
      },
      {
        "key": "moon_carrot",
        "display": "キャラット",
        "index": 3,
        "options": ["never", "rare", "uncommon", "default", "often", "mostly", "always", "insane"],
        "opts-display": ["なし", "ちっこい", "少ない", "デフォルト", "もっと", "いっぱい", "いっぱい", "インセイン"]
      },
      {
        "key": "moon_fruitdragon",
        "display": "サラマンダー",
        "index": 3,
        "options": ["never", "rare", "uncommon", "default", "often", "mostly", "always", "insane"],
        "opts-display": ["なし", "ちっこい", "少ない", "デフォルト", "もっと", "いっぱい", "いっぱい", "インセイン"]
      },
      {
        "key": "ocean_shoal",
        "display": "魚の群れ",
        "index": 3,
        "options": ["never", "rare", "uncommon", "default", "often", "mostly", "always", "insane"],
        "opts-display": ["なし", "ちっこい", "少ない", "デフォルト", "もっと", "いっぱい", "いっぱい", "インセイン"]
      },
      {
        "key": "ocean_wobsterden",
        "display": "ウォブスターマウンド",
        "index": 3,
        "options": ["never", "rare", "uncommon", "default", "often", "mostly", "always", "insane"],
        "opts-display": ["なし", "ちっこい", "少ない", "デフォルト", "もっと", "いっぱい", "いっぱい", "インセイン"]
      },
      {
        "key": "pigs",
        "display": "ブタ屋敷",
        "index": 3,
        "options": ["never", "rare", "uncommon", "default", "often", "mostly", "always", "insane"],
        "opts-display": ["なし", "ちっこい", "少ない", "デフォルト", "もっと", "いっぱい", "いっぱい", "インセイン"]
      },
      {
        "key": "rabbits",
        "display": "ウサギの穴",
        "index": 3,
        "options": ["never", "rare", "uncommon", "default", "often", "mostly", "always", "insane"],
        "opts-display": ["なし", "ちっこい", "少ない", "デフォルト", "もっと", "いっぱい", "いっぱい", "インセイン"]
      }
    ]
  },
  {
    "name": "monsters",
    "display": "敵対生物とスポナー",
    "items": [
      {
        "key": "angrybees",
        "display": "キラー蜂の巣",
        "index": 3,
        "options": ["never", "rare", "uncommon", "default", "often", "mostly", "always", "insane"],
        "opts-display": ["なし", "ちっこい", "少ない", "デフォルト", "もっと", "いっぱい", "いっぱい", "インセイン"]
      },
      {
        "key": "chess",
        "display": "ぜんまい仕掛けの駒",
        "index": 3,
        "options": ["never", "rare", "uncommon", "default", "often", "mostly", "always", "insane"],
        "opts-display": ["なし", "ちっこい", "少ない", "デフォルト", "もっと", "いっぱい", "いっぱい", "インセイン"]
      },
      {
        "key": "houndmound",
        "display": "ハウンドの巣",
        "index": 3,
        "options": ["never", "rare", "uncommon", "default", "often", "mostly", "always", "insane"],
        "opts-display": ["なし", "ちっこい", "少ない", "デフォルト", "もっと", "いっぱい", "いっぱい", "インセイン"]
      },
      {
        "key": "merm",
        "display": "雨漏り小屋",
        "index": 3,
        "options": ["never", "rare", "uncommon", "default", "often", "mostly", "always", "insane"],
        "opts-display": ["なし", "ちっこい", "少ない", "デフォルト", "もっと", "いっぱい", "いっぱい", "インセイン"]
      },
      {
        "key": "moon_spiders",
        "display": "壊されたクモの穴",
        "index": 3,
        "options": ["never", "rare", "uncommon", "default", "often", "mostly", "always", "insane"],
        "opts-display": ["なし", "ちっこい", "少ない", "デフォルト", "もっと", "いっぱい", "いっぱい", "インセイン"]
      },
      {
        "key": "ocean_waterplant",
        "display": "海の雑草",
        "index": 3,
        "options": ["ocean_never", "ocean_rare", "ocean_uncommon", "ocean_default", "ocean_often", "ocean_mostly", "ocean_always", "ocean_insane"],
        "opts-display": ["なし", "ちっこい", "少ない", "デフォルト", "もっと", "いっぱい", "いっぱい", "インセイン"]
      },
      {
        "key": "spiders",
        "display": "クモの巣穴",
        "index": 3,
        "options": ["never", "rare", "uncommon", "default", "often", "mostly", "always", "insane"],
        "opts-display": ["なし", "ちっこい", "少ない", "デフォルト", "もっと", "いっぱい", "いっぱい", "インセイン"]
      },
      {
        "key": "tallbirds",
        "display": "アシナガ",
        "index": 3,
        "options": ["never", "rare", "uncommon", "default", "often", "mostly", "always", "insane"],
        "opts-display": ["なし", "ちっこい", "少ない", "デフォルト", "もっと", "いっぱい", "いっぱい", "インセイン"]
      },
      {
        "key": "tentacles",
        "display": "触手",
        "index": 3,
        "options": ["never", "rare", "uncommon", "default", "often", "mostly", "always", "insane"],
        "opts-display": ["なし", "ちっこい", "少ない", "デフォルト", "もっと", "いっぱい", "いっぱい", "インセイン"]
      },
      {
        "key": "walrus",
        "display": "チウィーセの仮住まい",
        "index": 3,
        "options": ["never", "rare", "uncommon", "default", "often", "mostly", "always", "insane"],
        "opts-display": ["なし", "ちっこい", "少ない", "デフォルト", "もっと", "いっぱい", "いっぱい", "インセイン"]
      }
    ]
  }
]
